signalpy/404.tmp
signalpy/500.tmp
signalpy/__init__.py
signalpy/app.py
signalpy/base.tmp
signalpy/data.py
signalpy/jslib.py
SignalPy-1.0.6.dist-info/LICENSE.txt
SignalPy-1.0.6.dist-info/METADATA
SignalPy-1.0.6.dist-info/WHEEL
SignalPy-1.0.6.dist-info/top_level.txt
SignalPy-1.0.6.dist-info/RECORD
